cs/app/osx/misc.py
cs.app.osx.misc-20240622.1.dist-info/METADATA
cs.app.osx.misc-20240622.1.dist-info/WHEEL
cs.app.osx.misc-20240622.1.dist-info/top_level.txt
cs.app.osx.misc-20240622.1.dist-info/RECORD
